{
    "_comment": "Сопоставление пользователей: cloud_user_id -> box_user_id. null = пользователь не найден на коробке. При миграции лида: ASSIGNED_BY_ID = users[cloud_id] ?? 1 (admin).",
    "source_url": "https:\/\/milleniummed.bitrix24.ru",
    "target_url": "https:\/\/bitrix.milleniummedc.ru",
    "created_at": "2026-03-18T10:07:57+00:00",
    "users": {
        "1": 7,
        "46": 8,
        "56": 9,
        "84": 10,
        "86": 11,
        "88": 12,
        "94": 13,
        "96": 14,
        "98": 15,
        "104": 16,
        "110": 17,
        "112": 18,
        "356": 19,
        "358": 20,
        "360": 21,
        "362": 22,
        "364": 23,
        "368": 24,
        "372": 25,
        "592": 26,
        "704": 27,
        "966": 28,
        "1672": 29,
        "1690": 30,
        "1728": 31,
        "1800": 32,
        "1834": 33,
        "1840": 34,
        "1864": 35,
        "1884": 36,
        "1888": 37,
        "1924": 38,
        "1926": 39,
        "1928": 40,
        "1938": 41,
        "1962": 42,
        "1964": 43,
        "1966": 4,
        "1968": 44,
        "1970": 45,
        "1972": 6,
        "1974": 46,
        "1976": 47,
        "1978": null,
        "1980": null,
        "1982": null
    }
}